LICENSE
MANIFEST.in
README.rst
setup.py
orator_cache/__init__.py
orator_cache/cache.py
orator_cache/database_manager.py
orator_cache/utils.py
orator_cache/version.py
orator_cache.egg-info/PKG-INFO
orator_cache.egg-info/SOURCES.txt
orator_cache.egg-info/dependency_links.txt
orator_cache.egg-info/pbr.json
orator_cache.egg-info/requires.txt
orator_cache.egg-info/top_level.txt
orator_cache/query/__init__.py
orator_cache/query/cached_builder.py