Metadata-Version: 1.1
Name: orator-cache
Version: 0.1.1
Summary: Orator ORM official extension providing cache functionality.
Home-page: https://github.com/sdispater/orator-cache
Author: Sébastien Eustace
Author-email: sebastien.eustace@gmail.com
License: MIT
Download-URL: https://github.com/sdispater/orator-cache/archive/0.1.1.tar.gz
Platform: UNKNOWN
Classifier: Intended Audience :: Developers
Classifier: Operating System :: OS Independent
Classifier: Programming Language :: Python
Classifier: Topic :: Software Development :: Libraries :: Python Modules
